dendrite_python_sdk/__init__.py
dendrite_python_sdk/ai_util/__init__.py
dendrite_python_sdk/ai_util/generate_text.py
dendrite_python_sdk/dendrite_browser/ActivePageManager.py
dendrite_python_sdk/dendrite_browser/DendriteBrowser.py
dendrite_python_sdk/dendrite_browser/DendriteLocator.py
dendrite_python_sdk/dendrite_browser/DendritePage.py
dendrite_python_sdk/dendrite_browser/ScreenshotManager.py
dendrite_python_sdk/dendrite_browser/common/status.py
dendrite_python_sdk/dendrite_browser/utils.py
dendrite_python_sdk/dto/GetInteractionDTO.py
dendrite_python_sdk/dto/GoogleSearchDTO.py
dendrite_python_sdk/dto/MakeInteractionDTO.py
dendrite_python_sdk/dto/ScrapePageDTO.py
dendrite_python_sdk/examples/get_steam_reviews.py
dendrite_python_sdk/examples/review_sentiment.py
dendrite_python_sdk/examples/send_discord_message.py
dendrite_python_sdk/examples/simple_example.py
dendrite_python_sdk/examples/yc.py
dendrite_python_sdk/exceptions/DendriteException.py
dendrite_python_sdk/exceptions/IncorrectOutcomeException.py
dendrite_python_sdk/exceptions/__init__.py
dendrite_python_sdk/models/LLMConfig.py
dendrite_python_sdk/models/PageDeltaInformation.py
dendrite_python_sdk/models/PageInformation.py
dendrite_python_sdk/models/__init__.py
dendrite_python_sdk/models.py
dendrite_python_sdk/request_handler.py
dendrite_python_sdk/responses/GoogleSearchResponse.py
dendrite_python_sdk/responses/InteractionResponse.py
dendrite_python_sdk/responses/ScrapePageResponse.py
dendrite_python_sdk/responses/__init__.py
dendrite_python_sdk-1.0.2.dist-info/LICENSE
dendrite_python_sdk-1.0.2.dist-info/METADATA
dendrite_python_sdk-1.0.2.dist-info/WHEEL
dendrite_python_sdk-1.0.2.dist-info/RECORD
