Metadata-Version: 2.1
Name: dendrite-python-sdk
Version: 1.0.2
Summary: 
Author: Charles Maddock
Author-email: charles@dendrite.se
Requires-Python: >=3.9,<4.0
Classifier: Programming Language :: Python :: 3
Classifier: Programming Language :: Python :: 3.9
Classifier: Programming Language :: Python :: 3.10
Classifier: Programming Language :: Python :: 3.11
Classifier: Programming Language :: Python :: 3.12
Requires-Dist: backoff (>=2.2.1,<3.0.0)
Requires-Dist: bs4 (>=0.0.2,<0.0.3)
Requires-Dist: lxml (>=5.2.1,<6.0.0)
Requires-Dist: openai (>=1.11.0,<2.0.0)
Requires-Dist: openpyxl (>=3.1.2,<4.0.0)
Requires-Dist: pandas (>=2.2.2,<3.0.0)
Requires-Dist: playwright (>=1.43.0,<2.0.0)
Requires-Dist: pydantic (>=2.6.0,<3.0.0)
Requires-Dist: python-dotenv (>=1.0.1,<2.0.0)
Requires-Dist: requests (>=2.31.0,<3.0.0)
Requires-Dist: typing-extensions (>=4.12.0,<5.0.0)
